torsposer/__init__.py
torsposer/__main__.py
torsposer/exposer.py
torsposer/utils.py
torsposer-1.0.1.dist-info/METADATA
torsposer-1.0.1.dist-info/WHEEL
torsposer-1.0.1.dist-info/entry_points.txt
torsposer-1.0.1.dist-info/RECORD
