Metadata-Version: 2.1
Name: torsposer
Version: 1.0.1
Summary: Expose Services to the TOR network automatically
License: MIT
Author: Dhrumil Mistry
Author-email: 56185972+dmdhrumilmistry@users.noreply.github.com
Requires-Python: >=3.8,<4.0
Classifier: License :: OSI Approved :: MIT License
Classifier: Programming Language :: Python :: 3
Classifier: Programming Language :: Python :: 3.8
Classifier: Programming Language :: Python :: 3.9
Classifier: Programming Language :: Python :: 3.10
Classifier: Programming Language :: Python :: 3.11
Project-URL: Bug Tracker, https://github.com/dmdhrumilmistry/torsposer/issues
Project-URL: Home, https://github.com/dmdhrumilmistry/torsposer
Project-URL: Ko-Fi, https://ko-fi.com/dmdhrumilmistry
Project-URL: PayPal, https://paypal.me/dmdhrumilmistry
Project-URL: Support, https://github.com/sponsors/dmdhrumilmistry/
